hwi-qt.py
hwi.py
hwilib/__init__.py
hwilib/_base58.py
hwilib/_bech32.py
hwilib/_cli.py
hwilib/_gui.py
hwilib/_script.py
hwilib/_serialize.py
hwilib/commands.py
hwilib/common.py
hwilib/descriptor.py
hwilib/devices/__init__.py
hwilib/devices/bitbox02.py
hwilib/devices/bitbox02_lib/LICENSE
hwilib/devices/bitbox02_lib/README.md
hwilib/devices/bitbox02_lib/__init__.py
hwilib/devices/bitbox02_lib/bitbox02/__init__.py
hwilib/devices/bitbox02_lib/bitbox02/bitbox02.py
hwilib/devices/bitbox02_lib/bitbox02/bootloader.py
hwilib/devices/bitbox02_lib/bitbox02/py.typed
hwilib/devices/bitbox02_lib/bitbox02/secp256k1.py
hwilib/devices/bitbox02_lib/communication/__init__.py
hwilib/devices/bitbox02_lib/communication/bitbox_api_protocol.py
hwilib/devices/bitbox02_lib/communication/communication.py
hwilib/devices/bitbox02_lib/communication/devices.py
hwilib/devices/bitbox02_lib/communication/generated/__init__.py
hwilib/devices/bitbox02_lib/communication/generated/antiklepto_pb2.py
hwilib/devices/bitbox02_lib/communication/generated/antiklepto_pb2.pyi
hwilib/devices/bitbox02_lib/communication/generated/backup_commands_pb2.py
hwilib/devices/bitbox02_lib/communication/generated/backup_commands_pb2.pyi
hwilib/devices/bitbox02_lib/communication/generated/bitbox02_system_pb2.py
hwilib/devices/bitbox02_lib/communication/generated/bitbox02_system_pb2.pyi
hwilib/devices/bitbox02_lib/communication/generated/btc_pb2.py
hwilib/devices/bitbox02_lib/communication/generated/btc_pb2.pyi
hwilib/devices/bitbox02_lib/communication/generated/cardano_pb2.py
hwilib/devices/bitbox02_lib/communication/generated/cardano_pb2.pyi
hwilib/devices/bitbox02_lib/communication/generated/common_pb2.py
hwilib/devices/bitbox02_lib/communication/generated/common_pb2.pyi
hwilib/devices/bitbox02_lib/communication/generated/eth_pb2.py
hwilib/devices/bitbox02_lib/communication/generated/eth_pb2.pyi
hwilib/devices/bitbox02_lib/communication/generated/hww_pb2.py
hwilib/devices/bitbox02_lib/communication/generated/hww_pb2.pyi
hwi-3.1.0.dist-info/LICENSE
hwi-3.1.0.dist-info/METADATA
hwi-3.1.0.dist-info/WHEEL
hwi-3.1.0.dist-info/entry_points.txt
hwi-3.1.0.dist-info/RECORD
