Metadata-Version: 2.1
Name: hwi
Version: 3.1.0
Summary: A library for working with Bitcoin hardware wallets
Home-page: https://github.com/bitcoin-core/HWI
License: MIT
Author: Ava Chow
Author-email: me@achow101.com
Requires-Python: >=3.8,<3.13
Classifier: License :: OSI Approved :: MIT License
Classifier: Programming Language :: Python :: 3
Classifier: Programming Language :: Python :: 3.8
Classifier: Programming Language :: Python :: 3.9
Classifier: Programming Language :: Python :: 3.10
Classifier: Programming Language :: Python :: 3.11
Classifier: Programming Language :: Python :: 3.12
Provides-Extra: qt
Requires-Dist: cbor2 (>=5.4.6,<6.0.0)
Requires-Dist: dataclasses (>=0.8,<0.9) ; python_version >= "3.6" and python_version < "3.7"
Requires-Dist: ecdsa (>=0,<1)
Requires-Dist: hidapi (>=0.14.0)
Requires-Dist: libusb1 (>=1.7,<4)
Requires-Dist: mnemonic (>=0,<1)
Requires-Dist: noiseprotocol (>=0.3.1,<0.4.0)
Requires-Dist: protobuf (>=4.23.3,<5.0.0)
Requires-Dist: pyaes (>=1.6,<2.0)
Requires-Dist: pyserial (>=3.5,<4.0)
Requires-Dist: pyside2 (>=5.14.0,<6.0.0) ; (python_version < "3.10") and (extra == "qt")
Requires-Dist: semver (>=3.0.1,<4.0.0)
Requires-Dist: typing-extensions (>=4.4,<5.0)
Project-URL: Repository, https://github.com/bitcoin-core/HWI
